NLPTextAugmentation/EDA.py
NLPTextAugmentation/MTLCombination.py
NLPTextAugmentation/SentenceBoundary.py
NLPTextAugmentation/Single.py
NLPTextAugmentation/Word2Vec.py
NLPTextAugmentation/__init__.py
NLPTextAugmentation/_version.py
NLPTextAugmentation/utils.py
NLPTextAugmentation-1.0.0.dist-info/LICENSE
NLPTextAugmentation-1.0.0.dist-info/METADATA
NLPTextAugmentation-1.0.0.dist-info/WHEEL
NLPTextAugmentation-1.0.0.dist-info/top_level.txt
NLPTextAugmentation-1.0.0.dist-info/RECORD
